[{"id": 152795, "post_id": 211616, "name": "Agastya Bhattacharya", "email": "bhattacharya_agastya@schumm.test", "body": "Laudantium nobis delectus."}, {"id": 152794, "post_id": 211616, "name": "Girja Embranthiri Jr.", "email": "girja_jr_embranthiri@volkman.example", "body": "Ea nobis voluptas. Vitae voluptatem rem."}, {"id": 152793, "post_id": 211615, "name": "Dipendra Dubashi Esq.", "email": "dubashi_dipendra_esq@friesen.test", "body": "Ullam et quasi. Reiciendis corporis iure. Labore magnam et."}, {"id": 152792, "post_id": 211614, "name": "Omana Prajapat IV", "email": "iv_omana_prajapat@skiles.example", "body": "Provident accusantium assumenda. Facere fugit consequatur. Doloribus est laudantium. Quia assumenda ipsum."}, {"id": 152791, "post_id": 211614, "name": "Gautam Tagore", "email": "tagore_gautam@schneider.example", "body": "Harum dolor vitae."}, {"id": 152790, "post_id": 211613, "name": "Surya Dutta JD", "email": "surya_dutta_jd@kling-macgyver.test", "body": "Quasi aliquid molestias."}, {"id": 152789, "post_id": 211612, "name": "Laxman Banerjee", "email": "banerjee_laxman@schaden.test", "body": "Sed odit voluptatum."}, {"id": 152788, "post_id": 211605, "name": "Umang Somayaji", "email": "somayaji_umang@zboncak.test", "body": "Aliquam in voluptatem. Asperiores optio excepturi. Omnis nostrum quam."}, {"id": 152787, "post_id": 211605, "name": "Sanjay Kaul", "email": "kaul_sanjay@bartoletti-morar.example", "body": "Eos natus officiis. Animi et tempora. Et sed similique."}, {"id": 152786, "post_id": 211604, "name": "Arun Varma II", "email": "ii_varma_arun@ebert-kuhn.example", "body": "Tempora odio quas. Ad temporibus ab."}]